param/__init__.py
param/command.py
param/make.py
param/multi_value.py
param/optional.py
param/param.py
param/single_value.py
tool/__init__.py
tool/gcc.py
tool/make.py
tool/nasm.py
tool/utility.py
namke-1.0.0.dist-info/METADATA
namke-1.0.0.dist-info/WHEEL
namke-1.0.0.dist-info/top_level.txt
namke-1.0.0.dist-info/RECORD
