Metadata-Version: 2.1
Name: namke
Version: 1.0.0
Summary: nagisa make, for nasm, c and c plus plus
Author: nagisa
Author-email: 1300296933@qq.com
